{
  "sourceId": "przychodniawitomino",
  "sourceName": "Przychodnia Witomino",
  "baseUrl": "https://przychodniawitomino.pl/praca/",
  "city": "Gdańsk",
  "facilityName": "Przychodnia Witomino",
  "selectors": {
    "jobListContainer": null,
    "jobItem": "article, .post, .entry, div.job, div.oferta",
    "title": "h1, h2, h3, .title, .job-title",
    "link": "a",
    "description": null
  },
  "extraction": {
    "titleFrom": "text",
    "linkFrom": "href",
    "normalizeLink": true
  },
  "pagination": {
    "type": "none",
    "param": "page",
    "maxPages": 10
  },
  "metadata": {
    "confidence": "LOW",
    "autoGenerated": false,
    "verifiedBy": "manual",
    "notes": "Small facility - may have no active postings. Config created manually. May need adjustment based on actual page structure.",
    "requiresPlaywright": false,
    "needsReview": true
  }
}

